mysec/__init__.py
mysec/figures.py
mysec/models.py
mysec/queries.py
mysec/services.py
mysec-0.8.0.dist-info/METADATA
mysec-0.8.0.dist-info/WHEEL
mysec-0.8.0.dist-info/licenses/LICENSE
mysec-0.8.0.dist-info/RECORD
