Metadata-Version: 2.4
Name: mysec
Version: 0.8.0
Summary: 
License-File: LICENSE
Author: aan
Author-email: andoludovic.andriamamonjy@gmail.com
Requires-Python: >=3.11,<3.13
Classifier: Programming Language :: Python :: 3
Classifier: Programming Language :: Python :: 3.11
Classifier: Programming Language :: Python :: 3.12
Requires-Dist: bearishpy (>=0.41.0,<1.0.0)
Requires-Dist: plotly (>=4.12.0,<6.0.0)
